{
  "name": "Allergy",
  "fields": [
    {
      "fieldName": "allergy",
      "fieldType": "String"
    }
  ],
  "relationships": [
    {
      "relationshipName": "applicationInfo",
      "otherEntityName": "applicationInfo",
      "relationshipType": "many-to-one",
      "otherEntityField": "id"
    }
  ],
  "changelogDate": "20190709151747",
  "javadoc": "Information about allergic reactions",
  "entityTableName": "allergy",
  "dto": "mapstruct",
  "pagination": "pagination",
  "service": "serviceImpl",
  "jpaMetamodelFiltering": false,
  "fluentMethods": true,
  "clientRootFolder": "",
  "applications": "*"
}
